{
    "version": "1.0.0",
    "name": "Marvin chair",
    "assetPath": "characters/shucks/marvin-shucks-chair/",
    "singTime": 4,
    "isPixel": false,
    "scale": 3.6,
    "healthIcon": {
        "id": "marvin-shucks-bloody",
        "isPixel": false,
        "flipX": false,
        "scale": 1
    },
    "animations": [
        {
            "name": "idle",
            "prefix": "i",
            "offsets": [
                245,
                64
            ],
            "frameRate": 24,
            "frameIndices": []
        },
        {
            "name": "singLEFTmiss",
            "prefix": "ml",
            "offsets": [
                340,
                640
            ],
            "frameRate": 24,
            "frameIndices": []
        },
        {
            "name": "singRIGHT",
            "prefix": "r",
            "offsets": [
                245,
                64
            ],
            "frameRate": 24,
            "frameIndices": []
        },
        {
            "name": "singRIGHTmiss",
            "prefix": "mr",
            "offsets": [
                260,
                570
            ],
            "frameRate": 24,
            "frameIndices": []
        },
        {
            "name": "singUPmiss",
            "prefix": "mu",
            "offsets": [
                241,
                830
            ],
            "frameRate": 24,
            "frameIndices": []
        },
        {
            "name": "singUP",
            "prefix": "u",
            "offsets": [
                245,
                64
            ],
            "frameRate": 24,
            "frameIndices": []
        },
        {
            "name": "singDOWNmiss",
            "prefix": "md",
            "offsets": [
                305,
                430
            ],
            "frameRate": 24,
            "frameIndices": []
        },
        {
            "name": "singDOWN",
            "prefix": "d",
            "offsets": [
                245,
                64
            ],
            "frameRate": 24,
            "frameIndices": []
        },
        {
            "name": "singLEFT",
            "prefix": "l",
            "offsets": [
                245,
                64
            ],
            "frameRate": 24,
            "frameIndices": []
        }
    ],
    "flipX": true
}